lotr_sdk.py
lotr_sdk_karol-1.dist-info/LICENSE.txt
lotr_sdk_karol-1.dist-info/METADATA
lotr_sdk_karol-1.dist-info/WHEEL
lotr_sdk_karol-1.dist-info/top_level.txt
lotr_sdk_karol-1.dist-info/RECORD
