Metadata-Version: 2.1
Name: lotr-sdk-karol
Version: 1
Summary: Lord of the rings SDK
Author: Karol Djanashvili
Classifier: Programming Language :: Python :: 3
Classifier: Programming Language :: Python :: 3.6
Classifier: Programming Language :: Python :: 3.7
License-File: LICENSE.txt
Requires-Dist: certifi (==2022.9.14)
Requires-Dist: charset-normalizer (==2.1.1)
Requires-Dist: idna (==3.4)
Requires-Dist: urllib3 (==1.26.12)
